{"posts_0e1cd7.md":"ea4dd30f","docs_doc2.md":"e00f394c","docs_doc3.md":"151fca14","docs_doc4.md":"1e203b91","docs_doc5.md":"a9b3c259","index.md":"457940e3","page1.md":"b0680ff4","page2.md":"22d13187","pages_archives.md":"d37d020a","pages_tags.md":"b1327e9d","posts_cd49a3.md":"d825735f","posts_1e9071.md":"8af16fe5","posts_d4bad3.md":"dbcc4f96","posts_c10a87.md":"ccab57f8","posts_73a18e.md":"a284a414","posts_e07056.md":"37263ead","posts_36fb63.md":"3faf8704","posts_2fc5ad.md":"53cde0f2","docs_doc1.md":"e87b748c","posts_b808f8.md":"7859a56e"}
